tpllib/.DS_Store
tpllib/__init__.py
tpllib/template/.DS_Store
tpllib/template/noprompt.tpl
tpllib/template/test.tpl
tpllib-0.0.1.dist-info/METADATA
tpllib-0.0.1.dist-info/WHEEL
tpllib-0.0.1.dist-info/RECORD
