Metadata-Version: 1.2
Name: tpllib
Version: 0.0.1
Summary: A library with jupyter nbconvert templates
Home-page: https://github.com/gonzolabs
License: UNKNOWN
Author: John Bohannon
Author-email: john@johnbohannon.org
Classifier: License :: OSI Approved :: MIT License
